openbadges_bakery/__init__.py
openbadges_bakery/cli.py
openbadges_bakery/png_bakery.py
openbadges_bakery/svg_bakery.py
openbadges_bakery/tests.py
openbadges_bakery/utils.py
openbadges_bakery/testfiles/baked_example.svg
openbadges_bakery/testfiles/baked_heart.png
openbadges_bakery/testfiles/public_domain_heart.png
openbadges_bakery/testfiles/unbaked_example.svg
openbadges_bakery-2.0.0.dist-info/LICENSE
openbadges_bakery-2.0.0.dist-info/METADATA
openbadges_bakery-2.0.0.dist-info/WHEEL
openbadges_bakery-2.0.0.dist-info/entry_points.txt
openbadges_bakery-2.0.0.dist-info/pbr.json
openbadges_bakery-2.0.0.dist-info/top_level.txt
openbadges_bakery-2.0.0.dist-info/RECORD
