Metadata-Version: 2.1
Name: openbadges-bakery
Version: 2.0.0
Summary: A python utility for baking and extracting Open Badges metadata from images.
Home-page: https://badgr.com
Author: Concentric Sky
Author-email: notto@concentricsky.com
License: Apache License 2.0
Platform: UNKNOWN
Classifier: Environment :: Console
Classifier: Development Status :: 3 - Alpha
Classifier: Intended Audience :: Developers
Classifier: License :: OSI Approved :: Apache Software License
Classifier: Operating System :: OS Independent
Classifier: Programming Language :: Python
Classifier: Programming Language :: Python :: 3
Classifier: Programming Language :: Python :: 3.6
Classifier: Topic :: Internet :: WWW/HTTP
Classifier: Topic :: Education
Classifier: Topic :: Utilities
Classifier: Intended Audience :: Developers
License-File: LICENSE
Requires-Dist: Click (>=6.6)
Requires-Dist: pypng (>=0.0.20)
Requires-Dist: defusedxml (<1.0,>=0.6.0)
Requires-Dist: rfc3986 (>=1.5.0)
Requires-Dist: six (>=1.16.0)
